src/__init__.py
src/scripts/__init__.py
src/scripts/agent_table_processing.py
src/scripts/authenticity_institution.py
src/scripts/authenticity_person.py
src/scripts/authenticity_space.py
src/scripts/process_Institution.py
src/scripts/process_Person.py
src/scripts/process_Space.py
src/scripts/readactor.py
tests/__init__.py
tests/test_Institution.py
tests/test_Person.py
tests/test_Space.py
tests/test_click.py
ReadActor-2.0.3.dist-info/LICENSE
ReadActor-2.0.3.dist-info/METADATA
ReadActor-2.0.3.dist-info/WHEEL
ReadActor-2.0.3.dist-info/entry_points.txt
ReadActor-2.0.3.dist-info/top_level.txt
ReadActor-2.0.3.dist-info/RECORD
