Metadata-Version: 2.1
Name: ReadActor
Version: 2.0.3
Summary: A lookup tool for ReadChina project
Home-page: https://github.com/readchina/ReadActor
Author: Qin Gu
Author-email: guqin7@gmail.com
Project-URL: Bug Tracker, https://github.com/pypa/ReadActor/issues
Classifier: Programming Language :: Python :: 3
Classifier: License :: OSI Approved :: MIT License
Classifier: Operating System :: OS Independent
Requires-Python: >=3.8
License-File: LICENSE
Requires-Dist: Click
Requires-Dist: pandas
Requires-Dist: requests
